{"frames":{"mon1":{"frame":{"x":74,"y":8,"w":63,"h":150},"rotated":false,"trimmed":false,"spriteSourceSize":{"x":0,"y":0,"w":63,"h":150},"sourceSize":{"w":63,"h":150}},"mon2":{"frame":{"x":185,"y":55,"w":122,"h":78},"rotated":false,"trimmed":false,"spriteSourceSize":{"x":0,"y":0,"w":122,"h":78},"sourceSize":{"w":122,"h":78}},"mon3":{"frame":{"x":339,"y":75,"w":92,"h":84},"rotated":false,"trimmed":false,"spriteSourceSize":{"x":0,"y":0,"w":92,"h":84},"sourceSize":{"w":92,"h":84}},"mon4":{"frame":{"x":453,"y":76,"w":100,"h":83},"rotated":false,"trimmed":false,"spriteSourceSize":{"x":0,"y":0,"w":100,"h":83},"sourceSize":{"w":100,"h":83}},"mon5":{"frame":{"x":575,"y":76,"w":164,"h":67},"rotated":false,"trimmed":false,"spriteSourceSize":{"x":0,"y":0,"w":164,"h":67},"sourceSize":{"w":164,"h":67}},"mon6":{"frame":{"x":759,"y":77,"w":148,"h":73},"rotated":false,"trimmed":false,"spriteSourceSize":{"x":0,"y":0,"w":148,"h":73},"sourceSize":{"w":148,"h":73}},"mon7":{"frame":{"x":930,"y":81,"w":120,"h":77},"rotated":false,"trimmed":false,"spriteSourceSize":{"x":0,"y":0,"w":120,"h":77},"sourceSize":{"w":120,"h":77}},"ox1":{"frame":{"x":0,"y":172,"w":148,"h":83},"rotated":false,"trimmed":false,"spriteSourceSize":{"x":0,"y":0,"w":148,"h":83},"sourceSize":{"w":148,"h":83}},"ox2":{"frame":{"x":159,"y":172,"w":145,"h":83},"rotated":false,"trimmed":false,"spriteSourceSize":{"x":0,"y":0,"w":145,"h":83},"sourceSize":{"w":145,"h":83}},"ox3":{"frame":{"x":309,"y":172,"w":144,"h":82},"rotated":false,"trimmed":false,"spriteSourceSize":{"x":0,"y":0,"w":144,"h":82},"sourceSize":{"w":144,"h":82}},"ox5":{"frame":{"x":616,"y":172,"w":144,"h":83},"rotated":false,"trimmed":false,"spriteSourceSize":{"x":0,"y":0,"w":144,"h":83},"sourceSize":{"w":144,"h":83}},"ox6":{"frame":{"x":766,"y":172,"w":145,"h":83},"rotated":false,"trimmed":false,"spriteSourceSize":{"x":0,"y":0,"w":145,"h":83},"sourceSize":{"w":145,"h":83}},"ox4":{"frame":{"x":464,"y":173,"w":145,"h":81},"rotated":false,"trimmed":false,"spriteSourceSize":{"x":0,"y":0,"w":145,"h":81},"sourceSize":{"w":145,"h":81}},"bun4":{"frame":{"x":317,"y":259,"w":69,"h":80},"rotated":false,"trimmed":false,"spriteSourceSize":{"x":0,"y":0,"w":69,"h":80},"sourceSize":{"w":69,"h":80}},"bun3":{"frame":{"x":231,"y":266,"w":66,"h":79},"rotated":false,"trimmed":false,"spriteSourceSize":{"x":0,"y":0,"w":66,"h":79},"sourceSize":{"w":66,"h":79}},"bun5":{"frame":{"x":396,"y":266,"w":99,"h":75},"rotated":false,"trimmed":false,"spriteSourceSize":{"x":0,"y":0,"w":99,"h":75},"sourceSize":{"w":99,"h":75}},"bun1":{"frame":{"x":5,"y":267,"w":104,"h":84},"rotated":false,"trimmed":false,"spriteSourceSize":{"x":0,"y":0,"w":104,"h":84},"sourceSize":{"w":104,"h":84}},"bun2":{"frame":{"x":132,"y":268,"w":78,"h":82},"rotated":false,"trimmed":false,"spriteSourceSize":{"x":0,"y":0,"w":78,"h":82},"sourceSize":{"w":78,"h":82}},"bun6":{"frame":{"x":519,"y":282,"w":121,"h":71},"rotated":false,"trimmed":false,"spriteSourceSize":{"x":0,"y":0,"w":121,"h":71},"sourceSize":{"w":121,"h":71}}},"meta":{"app":"https://www.leshylabs.com/apps/sstool/","version":"Leshy SpriteSheet Tool v0.8.4","image":"playersheet.png","size":{"w":1058,"h":371},"scale":1}}